CondDBBrowser/__init__.py
CondDBBrowser/__main__.py
CondDBBrowser/CondDBUI/GitBridge.py
CondDBBrowser/CondDBUI/__init__.py
CondDBBrowser/CondDBUI/Browser/Dialogs.py
CondDBBrowser/CondDBUI/Browser/Main.py
CondDBBrowser/CondDBUI/Browser/MainWindow.py
CondDBBrowser/CondDBUI/Browser/Models.py
CondDBBrowser/CondDBUI/Browser/Resources_rc.py
CondDBBrowser/CondDBUI/Browser/Ui_AddConditionDialog.py
CondDBBrowser/CondDBUI/Browser/Ui_CreateSliceDialog.py
CondDBBrowser/CondDBUI/Browser/Ui_DumpToFilesDialog.py
CondDBBrowser/CondDBUI/Browser/Ui_EditConditionPayloadDialog.py
CondDBBrowser/CondDBUI/Browser/Ui_FindDialog.py
CondDBBrowser/CondDBUI/Browser/Ui_MainWindow.py
CondDBBrowser/CondDBUI/Browser/Ui_NewDatabaseDialog.py
CondDBBrowser/CondDBUI/Browser/Ui_NewNodeDialog.py
CondDBBrowser/CondDBUI/Browser/Ui_NewTagDialog.py
CondDBBrowser/CondDBUI/Browser/Ui_OpenDatabaseDialog.py
CondDBBrowser/CondDBUI/Browser/Ui_SelectTagDialog.py
CondDBBrowser/CondDBUI/Browser/Utils.py
CondDBBrowser/CondDBUI/Browser/Widgets.py
CondDBBrowser/CondDBUI/Browser/__init__.py
CondDBBrowser/GitCondDB/GitAccess.py
CondDBBrowser/GitCondDB/IOVs.py
CondDBBrowser/GitCondDB/Payload.py
CondDBBrowser/GitCondDB/Tags.py
CondDBBrowser/GitCondDB/__init__.py
CondDBBrowser/GitCondDB/_helpers.py
CondDBBrowser-0.1.3.dist-info/COPYING
CondDBBrowser-0.1.3.dist-info/METADATA
CondDBBrowser-0.1.3.dist-info/WHEEL
CondDBBrowser-0.1.3.dist-info/entry_points.txt
CondDBBrowser-0.1.3.dist-info/top_level.txt
CondDBBrowser-0.1.3.dist-info/zip-safe
CondDBBrowser-0.1.3.dist-info/RECORD
