Metadata-Version: 2.1
Name: CondDBBrowser
Version: 0.1.3
Summary: LHCb Conditions Database Browser
Home-page: https://gitlab.cern.ch/lhcb/CondDBBrowser
Author: CERN - LHCb Core Software
Author-email: lhcb-core-soft@cern.ch
License: UNKNOWN
Platform: UNKNOWN
Classifier: Development Status :: 4 - Beta
Classifier: Intended Audience :: Developers
Classifier: License :: OSI Approved :: GNU General Public License v3 (GPLv3)
Classifier: Programming Language :: Python :: 2
Classifier: Programming Language :: Python :: 2.7
Requires-Dist: PySide2 (==5.12.0)
Requires-Dist: shiboken2 (==5.12)
